jupyter_starters/__init__.py
jupyter_starters/_version.py
jupyter_starters/app.py
jupyter_starters/handlers.py
jupyter_starters/json_.py
jupyter_starters/manager.py
jupyter_starters/serverextension.py
jupyter_starters/trait_types.py
jupyter_starters/types.py
jupyter_starters/etc/install.json
jupyter_starters/etc/jupyter-starters-serverextension.json
jupyter_starters/labextension/package.json
jupyter_starters/labextension/static/115.1fd6aa8a6a9555dc515f.js
jupyter_starters/labextension/static/122.a983627679e2a2668c30.js
jupyter_starters/labextension/static/292.e344de089fe3beb15b9f.js
jupyter_starters/labextension/static/34.86f749bf96c66d2b67c4.js
jupyter_starters/labextension/static/591.ed520d8343b99dea0382.js
jupyter_starters/labextension/static/647.67d4387ff9a736fec9a8.js
jupyter_starters/labextension/static/647.67d4387ff9a736fec9a8.js.LICENSE.txt
jupyter_starters/labextension/static/730.2d94af0d143c35e37c26.js
jupyter_starters/labextension/static/75.806752c9539d092a02ca.js
jupyter_starters/labextension/static/786.7a40a24ad0db0931aeaa.js
jupyter_starters/labextension/static/814.e287f8d0963e5a63fb7f.js
jupyter_starters/labextension/static/824.6b002d8e29f2f89e49bb.js
jupyter_starters/labextension/static/97.1a2fbf4fc01719c55363.js
jupyter_starters/labextension/static/98.e55d98bce8026516b0fc.js
jupyter_starters/labextension/static/remoteEntry.f032d7d8606922f9314f.js
jupyter_starters/labextension/static/style.js
jupyter_starters/labextension/static/third-party-licenses.json
jupyter_starters/py_starters/__init__.py
jupyter_starters/py_starters/cookiecutter.py
jupyter_starters/py_starters/notebook.py
jupyter_starters/schema/__init__.py
jupyter_starters/schema/v2.json
jupyter_starters/schema/v2.py
jupyter_starters/tests/__init__.py
jupyter_starters/tests/conftest.py
jupyter_starters/tests/test_cli.py
jupyter_starters/tests/test_meta.py
jupyter_starters/tests/test_notebook.py
jupyter_starters/tests/test_src.py
jupyter_starters-1.1.0.dist-info/LICENSE
jupyter_starters-1.1.0.dist-info/METADATA
jupyter_starters-1.1.0.dist-info/WHEEL
jupyter_starters-1.1.0.dist-info/entry_points.txt
jupyter_starters-1.1.0.dist-info/top_level.txt
jupyter_starters-1.1.0.dist-info/RECORD
