Metadata-Version: 2.1
Name: jupyter-starters
Version: 1.1.0
Summary: Parametrized starter files and folders for Jupyter
Home-page: https://github.com/deathbeds/jupyterlab-starters
Author: dead pixels collective
Author-email: deathbeds@groups.google.com
License: BSD-3-Clause
Keywords: Interactive,Interpreter,Shell,Web,Jupyter,JupyterLab
Platform: UNKNOWN
Classifier: Framework :: Jupyter
Classifier: Framework :: Jupyter :: JupyterLab
Classifier: Framework :: Jupyter :: JupyterLab :: 3
Classifier: Framework :: Jupyter :: JupyterLab :: Extensions
Classifier: Framework :: Jupyter :: JupyterLab :: Extensions :: Prebuilt
Classifier: Intended Audience :: Developers
Classifier: Intended Audience :: Information Technology
Classifier: License :: OSI Approved :: BSD License
Classifier: Programming Language :: Python
Classifier: Programming Language :: Python :: 3
Classifier: Programming Language :: Python :: 3 :: Only
Classifier: Programming Language :: Python :: 3.10
Classifier: Programming Language :: Python :: 3.7
Classifier: Programming Language :: Python :: 3.8
Classifier: Programming Language :: Python :: 3.9
Requires-Python: >=3.7
License-File: LICENSE
Requires-Dist: jupyterlab (>=3)
Requires-Dist: jupyter-client (>=6.1.0)
